termingpt/__init__.py
termingpt/main.py
termingpt-2.0.1.dist-info/licenses/LICENSE
termingpt-2.0.1.dist-info/METADATA
termingpt-2.0.1.dist-info/WHEEL
termingpt-2.0.1.dist-info/entry_points.txt
termingpt-2.0.1.dist-info/top_level.txt
termingpt-2.0.1.dist-info/RECORD
