Metadata-Version: 2.4
Name: termingpt
Version: 2.0.1
Summary: AI-powered terminal assistant with production-ready code generation and security scanning
Home-page: https://github.com/thenoob4/termingpt
Author: TheNooB
Author-email: codelearh@gmail.com
Project-URL: Bug Reports, https://github.com/thenoob4/termingpt/issues
Project-URL: Source, https://github.com/thenoob4/termingpt
Project-URL: Documentation, https://github.com/thenoob4/termingpt#readme
Keywords: ai chatgpt gpt-4 code-generator terminal security-scanner cli assistant termux
Classifier: Development Status :: 5 - Production/Stable
Classifier: Intended Audience :: Developers
Classifier: Topic :: Software Development :: Code Generators
Classifier: Topic :: System :: Systems Administration
Classifier: Topic :: Security
Classifier: License :: OSI Approved :: MIT License
Classifier: Programming Language :: Python :: 3
Classifier: Programming Language :: Python :: 3.7
Classifier: Programming Language :: Python :: 3.8
Classifier: Programming Language :: Python :: 3.9
Classifier: Programming Language :: Python :: 3.10
Classifier: Programming Language :: Python :: 3.11
Classifier: Programming Language :: Python :: 3.12
Classifier: Operating System :: OS Independent
Requires-Python: >=3.7
License-File: LICENSE
Requires-Dist: requests>=2.25.0
Dynamic: author
Dynamic: author-email
Dynamic: classifier
Dynamic: description
Dynamic: description-content-type
Dynamic: home-page
Dynamic: keywords
Dynamic: license-file
Dynamic: project-url
Dynamic: requires-dist
Dynamic: requires-python
Dynamic: summary
